yalchemy/__init__.py
yalchemy/col_utils.py
yalchemy/pretty_yaml.py
yalchemy/sqla_utils.py
yalchemy/table_structures.py
yalchemy/version.py
yalchemy/tests/__init__.py
yalchemy/tests/test_col_utils.py
yalchemy/tests/test_pretty_yaml.py
yalchemy/tests/test_sqla_utils.py
yalchemy/tests/test_table_structures.py
yalchemy-0.2.15.dist-info/DESCRIPTION.rst
yalchemy-0.2.15.dist-info/METADATA
yalchemy-0.2.15.dist-info/RECORD
yalchemy-0.2.15.dist-info/WHEEL
yalchemy-0.2.15.dist-info/metadata.json
yalchemy-0.2.15.dist-info/pbr.json
yalchemy-0.2.15.dist-info/top_level.txt
